echo360/__init__.py
echo360/course.py
echo360/downloader.py
echo360/echo_exceptions.py
echo360/hls_downloader.py
echo360/main.py
echo360/naive_m3u8_parser.py
echo360/utils.py
echo360/videos.py
echo360/binary_downloader/__init__.py
echo360/binary_downloader/chromedriver.py
echo360/binary_downloader/downloader.py
echo360/binary_downloader/firefoxdriver.py
echo360/binary_downloader/phantomjs.py
echo360-3.0.dist-info/LICENSE
echo360-3.0.dist-info/METADATA
echo360-3.0.dist-info/WHEEL
echo360-3.0.dist-info/entry_points.txt
echo360-3.0.dist-info/top_level.txt
echo360-3.0.dist-info/RECORD
