Metadata-Version: 2.1
Name: echo360
Version: 3.0
Summary: Commandline tool for automated downloads of echo360 videos
Home-page: https://github.com/soraxas/echo360
Author: soraxas
Author-email: oscar@tinyiu.com
License: MIT
Project-URL: Documentation, https://github.com/soraxas/echo360/blob/master/README.md
Project-URL: Code, https://github.com/soraxas/echo360
Project-URL: Issue tracker, https://github.com/soraxas/echo360/issues
Platform: linux
Platform: macos
Platform: windows
Classifier: Programming Language :: Python :: 2
Classifier: Programming Language :: Python :: 3
Classifier: Programming Language :: Unix Shell
Classifier: Topic :: System :: Shells
Classifier: Topic :: System :: System Shells
Classifier: Topic :: Terminals
Classifier: Topic :: System :: Networking
Classifier: License :: OSI Approved :: MIT License
Requires-Python: >=2.7
License-File: LICENSE
Requires-Dist: python-dateutil >=2.2
Requires-Dist: selenium <4.1.4,>=2.44.0
Requires-Dist: ffmpy >=0.2.2
Requires-Dist: requests >=2.8.14
Requires-Dist: gevent >=1.2.2
Requires-Dist: wget >=3.2
Requires-Dist: pick ==0.6.7
Requires-Dist: tqdm
